sphinxcontrib/__init__.py
sphinxcontrib/citations/__init__.py
sphinxcontrib/citations/core.py
sphinxcontrib_citations-0.2.0.dist-info/LICENSE
sphinxcontrib_citations-0.2.0.dist-info/WHEEL
sphinxcontrib_citations-0.2.0.dist-info/METADATA
sphinxcontrib_citations-0.2.0.dist-info/RECORD
